README.md
setup.py
ta_scanner/version.py
ta_scanner.egg-info/PKG-INFO
ta_scanner.egg-info/SOURCES.txt
ta_scanner.egg-info/dependency_links.txt
ta_scanner.egg-info/top_level.txt