Metadata-Version: 2.1
Name: ta-scanner
Version: 0.0.1
Summary: Technical analysis scanner and bavhior matcher
Home-page: https://github.com/westonplatter/ta_scanner/
Author: Weston Platter
Author-email: westonplatter+github@gmail.com
License: BSD-3-Clause
Project-URL: Issue Tracker, https://github.com/westonplatter/ta_scanner/issues
Project-URL: Source Code, https://github.com/westonplatter/ta_scanner
Platform: UNKNOWN
Requires-Python: >=3.5
